README.txt
setup.cfg
setup.py
collective/__init__.py
collective.validator.xhtmlTransitional.egg-info/PKG-INFO
collective.validator.xhtmlTransitional.egg-info/SOURCES.txt
collective.validator.xhtmlTransitional.egg-info/dependency_links.txt
collective.validator.xhtmlTransitional.egg-info/entry_points.txt
collective.validator.xhtmlTransitional.egg-info/namespace_packages.txt
collective.validator.xhtmlTransitional.egg-info/not-zip-safe
collective.validator.xhtmlTransitional.egg-info/requires.txt
collective.validator.xhtmlTransitional.egg-info/top_level.txt
collective/validator/__init__.py
collective/validator/xhtmlTransitional/HISTORY.txt
collective/validator/xhtmlTransitional/README.txt
collective/validator/xhtmlTransitional/__init__.py
collective/validator/xhtmlTransitional/adapter.py
collective/validator/xhtmlTransitional/config.py
collective/validator/xhtmlTransitional/configure.zcml
collective/validator/xhtmlTransitional/refresh.txt
collective/validator/xhtmlTransitional/version.txt
collective/validator/xhtmlTransitional/i18n/collective.validator.xhtmlTransitional-it.po
collective/validator/xhtmlTransitional/interfaces/__init__.py
collective/validator/xhtmlTransitional/interfaces/interfaces.py
collective/validator/xhtmlTransitional/tests/__init__.py
collective/validator/xhtmlTransitional/tests/test_plone_validation.py