Metadata-Version: 1.0
Name: collective.validator.xhtmlTransitional
Version: 1.0.2beta
Summary: XHTML transitional Validator for collective.validator.base
Home-page: https://svn.plone.org/svn/collective/collective.validator.xhtmlTransitional
Author: Andrea Cecchi
Author-email: andrea.cecchi@redturtle.net
License: GPL
Keywords: Plone Validator XHTMLTransitional
Platform: UNKNOWN
Classifier: Framework :: Plone
Classifier: Framework :: Zope2
Classifier: Framework :: Zope3
Classifier: Programming Language :: Python
Classifier: Topic :: Software Development :: Libraries :: Python Modules
